entropic_measurement/__init__.py
entropic_measurement/correction.py
entropic_measurement/entropy.py
entropic_measurement/logger.py
entropic_measurement/measurement.py
entropic_measurement/utils.py
entropic_measurement-0.1.0.dist-info/licenses/LICENSE
entropic_measurement-0.1.0.dist-info/METADATA
entropic_measurement-0.1.0.dist-info/WHEEL
entropic_measurement-0.1.0.dist-info/top_level.txt
entropic_measurement-0.1.0.dist-info/RECORD
