Metadata-Version: 2.4
Name: entropic_measurement
Version: 0.1.0
Summary: A Python library for explicit correction and traceability of informational bias in scientific and industrial measurement
Author-email: Raphael Constantinis <raphael@constantinis.com>
License: Creative Commons Legal Code
Project-URL: Homepage, https://github.com/rconstant1/entropic_measurement
Project-URL: Documentation, https://github.com/rconstant1/entropic_measurement/wiki
Project-URL: Issues, https://github.com/rconstant1/entropic_measurement/issues
Classifier: Programming Language :: Python :: 3
Classifier: License :: CC0 1.0 Universal (CC0 1.0) Public Domain Dedication
Classifier: Operating System :: OS Independent
Classifier: Intended Audience :: Science/Research
Classifier: Topic :: Scientific/Engineering :: Information Analysis
Requires-Python: >=3.8
License-File: LICENSE
Requires-Dist: numpy
Requires-Dist: scipy
Requires-Dist: pandas
Dynamic: license-file
